restricted_input/__init__.py
restricted_input/__main__.py
restricted_input-0.3.0.dist-info/LICENSE
restricted_input-0.3.0.dist-info/METADATA
restricted_input-0.3.0.dist-info/WHEEL
restricted_input-0.3.0.dist-info/top_level.txt
restricted_input-0.3.0.dist-info/RECORD
