Metadata-Version: 2.1
Name: restricted-input
Version: 0.3.0
Summary: Alternative to classic input with support for restricting certain characters
Home-page: https://github.com/FuturisticGoo/restricted_input
Author: Aman Anifer
Author-email: fgoo.edu@hash.fyi
License: MIT
Keywords: input,filter input,restricted,getpass,integer,filter,smart
Platform: UNKNOWN
Classifier: License :: OSI Approved :: MIT License
Classifier: Operating System :: OS Independent
Classifier: Development Status :: 4 - Beta
Classifier: Topic :: Terminals
Classifier: Topic :: Utilities
Classifier: Programming Language :: Python :: 3.6
Classifier: Programming Language :: Python :: 3.7
Classifier: Programming Language :: Python :: 3.8
Classifier: Programming Language :: Python :: 3.9
Requires-Python: >= 3.6
